aiomisc/__init__.py
aiomisc/_context_vars.py
aiomisc/aggregate.py
aiomisc/backoff.py
aiomisc/circuit_breaker.py
aiomisc/compat.py
aiomisc/context.py
aiomisc/counters.py
aiomisc/cron.py
aiomisc/entrypoint.py
aiomisc/io.py
aiomisc/iterator_wrapper.py
aiomisc/log.py
aiomisc/periodic.py
aiomisc/pool.py
aiomisc/process_pool.py
aiomisc/py.typed
aiomisc/recurring.py
aiomisc/signal.py
aiomisc/thread_pool.py
aiomisc/timeout.py
aiomisc/utils.py
aiomisc/version.py
aiomisc/worker_pool.py
aiomisc/plugins/__init__.py
aiomisc/plugins/__main__.py
aiomisc/service/__init__.py
aiomisc/service/aiohttp.py
aiomisc/service/asgi.py
aiomisc/service/base.py
aiomisc/service/carbon.py
aiomisc/service/cron.py
aiomisc/service/grpc_server.py
aiomisc/service/periodic.py
aiomisc/service/process.py
aiomisc/service/profiler.py
aiomisc/service/raven.py
aiomisc/service/sdwatchdog.py
aiomisc/service/tcp.py
aiomisc/service/tls.py
aiomisc/service/tracer.py
aiomisc/service/udp.py
aiomisc/service/uvicorn.py
aiomisc/service/dns/__init__.py
aiomisc/service/dns/records.py
aiomisc/service/dns/service.py
aiomisc/service/dns/store.py
aiomisc/service/dns/tree.py
aiomisc/service/dns/zone.py
aiomisc-17.10.2.dist-info/licenses/COPYING
aiomisc_log/__init__.py
aiomisc_log/enum.py
aiomisc_log/py.typed
aiomisc_log/formatter/__init__.py
aiomisc_log/formatter/color.py
aiomisc_log/formatter/journald.py
aiomisc_log/formatter/json.py
aiomisc_log/formatter/rich.py
aiomisc_worker/__init__.py
aiomisc_worker/__main__.py
aiomisc_worker/forking.py
aiomisc_worker/process.py
aiomisc_worker/process_inner.py
aiomisc_worker/protocol.py
aiomisc_worker/py.typed
aiomisc_worker/worker.py
aiomisc-17.10.2.dist-info/METADATA
aiomisc-17.10.2.dist-info/WHEEL
aiomisc-17.10.2.dist-info/entry_points.txt
aiomisc-17.10.2.dist-info/top_level.txt
aiomisc-17.10.2.dist-info/RECORD
