Metadata-Version: 2.4
Name: aiomisc
Version: 17.10.2
Summary: aiomisc - miscellaneous utils for asyncio
Author-email: Dmitry Orlov <me@mosquito.su>
License-Expression: MIT
Project-URL: Homepage, https://github.com/aiokitchen/aiomisc
Project-URL: Source, https://github.com/aiokitchen/aiomisc
Project-URL: Tracker, https://github.com/aiokitchen/aiomisc/issues
Project-URL: Changelog, https://github.com/aiokitchen/aiomisc/blob/master/CHANGELOG.md
Project-URL: Documentation, https://docs.aiomisc.com/
Classifier: Development Status :: 5 - Production/Stable
Classifier: Framework :: AsyncIO
Classifier: Framework :: Pytest
Classifier: Framework :: aiohttp
Classifier: Intended Audience :: Developers
Classifier: Intended Audience :: Education
Classifier: Intended Audience :: Information Technology
Classifier: Intended Audience :: System Administrators
Classifier: Natural Language :: English
Classifier: Natural Language :: Russian
Classifier: Operating System :: MacOS
Classifier: Operating System :: Microsoft :: Windows
Classifier: Operating System :: POSIX :: Linux
Classifier: Operating System :: POSIX
Classifier: Programming Language :: Python :: 3
Classifier: Programming Language :: Python :: 3.10
Classifier: Programming Language :: Python :: 3.11
Classifier: Programming Language :: Python :: 3.12
Classifier: Programming Language :: Python :: 3.13
Classifier: Programming Language :: Python :: Implementation :: CPython
Classifier: Programming Language :: Python
Classifier: Topic :: Internet :: WWW/HTTP
Classifier: Topic :: Internet
Classifier: Topic :: Software Development :: Libraries :: Python Modules
Classifier: Topic :: Software Development :: Libraries
Classifier: Topic :: Software Development
Classifier: Topic :: System :: Archiving :: Compression
Classifier: Topic :: System :: Logging
Classifier: Topic :: System
Classifier: Topic :: Utilities
Classifier: Typing :: Typed
Requires-Python: >=3.10
License-File: COPYING
Requires-Dist: colorlog<7,>=6.0
Requires-Dist: logging-journald; platform_system == "Linux"
Requires-Dist: typing_extensions; python_version < "3.12"
Provides-Extra: aiohttp
Requires-Dist: aiohttp>3; extra == "aiohttp"
Provides-Extra: asgi
Requires-Dist: aiohttp-asgi>=0.5.2; extra == "asgi"
Provides-Extra: carbon
Requires-Dist: aiocarbon>=0.15; extra == "carbon"
Provides-Extra: cron
Requires-Dist: croniter<3,>=2.0; extra == "cron"
Provides-Extra: dns
Requires-Dist: dnslib>=0.9; extra == "dns"
Provides-Extra: grpc
Requires-Dist: grpcio>=1.56; extra == "grpc"
Requires-Dist: grpcio-tools>=1.56; extra == "grpc"
Requires-Dist: grpcio-reflection>=1.56; extra == "grpc"
Provides-Extra: raven
Requires-Dist: aiohttp>3; extra == "raven"
Requires-Dist: raven; extra == "raven"
Provides-Extra: rich
Requires-Dist: rich; extra == "rich"
Provides-Extra: uvicorn
Requires-Dist: uvicorn>=0.27; extra == "uvicorn"
Requires-Dist: asgiref>=3.7; extra == "uvicorn"
Provides-Extra: uvloop
Requires-Dist: uvloop<1,>=0.21; extra == "uvloop"
Dynamic: license-file
